<?xml version="1.0" encoding="UTF-8"?>
<entry xmlns="http://www.w3.org/2005/Atom" xmlns:A="urn:schemas-autodesk-com:partatom"><title>L-Angle-Profile</title><id></id><updated>2010-07-24T04:43:13Z</updated><A:taxonomy><term>adsk:revit</term><label>Autodesk Revit</label></A:taxonomy><A:taxonomy><term>adsk:revit:grouping</term><label>Autodesk Revit Grouping</label></A:taxonomy><category><term>Profiles</term><scheme>adsk:revit:grouping</scheme></category><link rel="design-2d" type="application/rfa" href="."><A:design-file><A:title>L-Angle-Profile.rfa</A:title><A:product>Revit</A:product><A:product-version>2009</A:product-version><A:updated>2010-07-24T04:43:13Z</A:updated></A:design-file></link><A:family type="user"><A:variationCount>1</A:variationCount><A:part type="user"><title>L4X4X5/8</title><y type="custom" typeOfParameter="Length">0' - 1 7/32"</y><x type="custom" typeOfParameter="Length">0' - 1 7/32"</x><t type="custom" typeOfParameter="Length">0' - 0 5/8"</t><k type="custom" typeOfParameter="Length">0' - 1"</k><d type="custom" typeOfParameter="Length">0' - 4"</d><b type="custom" typeOfParameter="Length">0' - 4"</b><W type="custom" typeOfParameter="Number">15.7</W><A type="custom" typeOfParameter="Area" units="SF">0.03</A></A:part></A:family></entry>
