<?xml version="1.0" encoding="UTF-8"?>
<entry xmlns="http://www.w3.org/2005/Atom" xmlns:A="urn:schemas-autodesk-com:partatom"><title>0146_M_WD_W_Skylight-Fixed (NZ)</title><id></id><updated>2010-07-24T05:53:36Z</updated><A:taxonomy><term>adsk:revit</term><label>Autodesk Revit</label></A:taxonomy><A:taxonomy><term>adsk:revit:grouping</term><label>Autodesk Revit Grouping</label></A:taxonomy><category><term>Windows</term><scheme>adsk:revit:grouping</scheme></category><link rel="design-2d" type="application/rfa" href="."><A:design-file><A:title>0146_M_WD_W_Skylight-Fixed (NZ).rfa</A:title><A:product>Revit</A:product><A:product-version>2009</A:product-version><A:updated>2010-07-24T05:53:36Z</A:updated></A:design-file></link><A:family type="user"><Host>Roof</Host><A:variationCount>5</A:variationCount><A:part type="user"><title>710 x 965</title><Operation type="system" typeOfParameter="Text">UserDefined</Operation><Keynote type="system" typeOfParameter="Text">45-24-005</Keynote><Assembly_Code displayName="Assembly Code" type="system" typeOfParameter="Text">B3020110</Assembly_Code><Frame type="custom" typeOfParameter="Material">&lt;By Category&gt;</Frame><Height type="system" typeOfParameter="Length" units="mm">965</Height><Sash type="custom" typeOfParameter="Material">&lt;By Category&gt;</Sash><Width type="system" typeOfParameter="Length" units="mm">710</Width></A:part><A:part type="user"><title>610 x 685</title><Operation type="system" typeOfParameter="Text">UserDefined</Operation><Keynote type="system" typeOfParameter="Text">45-24-003</Keynote><Assembly_Code displayName="Assembly Code" type="system" typeOfParameter="Text">B3020110</Assembly_Code><Frame type="custom" typeOfParameter="Material">&lt;By Category&gt;</Frame><Height type="system" typeOfParameter="Length" units="mm">685</Height><Sash type="custom" typeOfParameter="Material">&lt;By Category&gt;</Sash><Width type="system" typeOfParameter="Length" units="mm">610</Width></A:part><A:part type="user"><title>410 x 1170</title><Operation type="system" typeOfParameter="Text">UserDefined</Operation><Keynote type="system" typeOfParameter="Text">45-24-002</Keynote><Assembly_Code displayName="Assembly Code" type="system" typeOfParameter="Text">B3020110</Assembly_Code><Frame type="custom" typeOfParameter="Material">&lt;By Category&gt;</Frame><Height type="system" typeOfParameter="Length" units="mm">1170</Height><Sash type="custom" typeOfParameter="Material">&lt;By Category&gt;</Sash><Width type="system" typeOfParameter="Length" units="mm">410</Width></A:part><A:part type="user"><title>1120 x 1170</title><Operation type="system" typeOfParameter="Text">UserDefined</Operation><Keynote type="system" typeOfParameter="Text">45-24-006</Keynote><Assembly_Code displayName="Assembly Code" type="system" typeOfParameter="Text">B3020110</Assembly_Code><Frame type="custom" typeOfParameter="Material">&lt;By Category&gt;</Frame><Height type="system" typeOfParameter="Length" units="mm">1170</Height><Sash type="custom" typeOfParameter="Material">&lt;By Category&gt;</Sash><Width type="system" typeOfParameter="Length" units="mm">1120</Width></A:part><A:part type="user"><title>710 x 1830</title><Operation type="system" typeOfParameter="Text">UserDefined</Operation><Keynote type="system" typeOfParameter="Text">45-24-004</Keynote><Assembly_Code displayName="Assembly Code" type="system" typeOfParameter="Text">B3020110</Assembly_Code><Frame type="custom" typeOfParameter="Material">&lt;By Category&gt;</Frame><Height type="system" typeOfParameter="Length" units="mm">1830</Height><Sash type="custom" typeOfParameter="Material">&lt;By Category&gt;</Sash><Width type="system" typeOfParameter="Length" units="mm">710</Width></A:part></A:family></entry>
