<?xml version="1.0" encoding="UTF-8"?>
<entry xmlns="http://www.w3.org/2005/Atom" xmlns:A="urn:schemas-autodesk-com:partatom"><title>플래그 극</title><id></id><updated>2010-07-24T05:05:39Z</updated><A:taxonomy><term>adsk:revit</term><label>Autodesk Revit</label></A:taxonomy><A:taxonomy><term>adsk:revit:grouping</term><label>Autodesk Revit Grouping</label></A:taxonomy><category><term>Site</term><scheme>adsk:revit:grouping</scheme></category><link rel="design-2d" type="application/rfa" href="."><A:design-file><A:title>플래그 극.rfa</A:title><A:product>Revit</A:product><A:product-version>2009</A:product-version><A:updated>2010-07-24T05:05:39Z</A:updated></A:design-file></link><A:family type="user"><A:variationCount>3</A:variationCount><A:part type="user"><title>6 미터</title><___ displayName="베이스" type="custom" typeOfParameter="Length" units="mm">254</___><_높_ displayName="높이" type="custom" typeOfParameter="Length" units="mm">6096</_높_><__ displayName="상단" type="custom" typeOfParameter="Length" units="mm">203</__></A:part><A:part type="user"><title>9 미터</title><___ displayName="베이스" type="custom" typeOfParameter="Length" units="mm">250</___><_높_ displayName="높이" type="custom" typeOfParameter="Length" units="mm">9000</_높_><__ displayName="상단" type="custom" typeOfParameter="Length" units="mm">200</__></A:part><A:part type="user"><title>12 미터</title><___ displayName="베이스" type="custom" typeOfParameter="Length" units="mm">254</___><_높_ displayName="높이" type="custom" typeOfParameter="Length" units="mm">12192</_높_><__ displayName="상단" type="custom" typeOfParameter="Length" units="mm">203</__></A:part></A:family></entry>
