<?xml version="1.0" encoding="UTF-8"?>
<entry xmlns="http://www.w3.org/2005/Atom" xmlns:A="urn:schemas-autodesk-com:partatom"><title>0026_M_FU_S_84A_드레스룸_의자5</title><id></id><updated>2010-07-24T02:16:54Z</updated><A:taxonomy><term>adsk:revit</term><label>Autodesk Revit</label></A:taxonomy><A:taxonomy><term>adsk:revit:grouping</term><label>Autodesk Revit Grouping</label></A:taxonomy><category><term>Furniture</term><scheme>adsk:revit:grouping</scheme></category><link rel="design-2d" type="application/rfa" href="."><A:design-file><A:title>0026_M_FU_S_84A_드레스룸_의자5.rfa</A:title><A:product>Revit</A:product><A:product-version>2010 or later one</A:product-version><A:updated>2010-07-24T02:16:54Z</A:updated></A:design-file></link><A:family type="user"><A:variationCount>1</A:variationCount><A:part type="user"><title>KO-Office chair OH 2490  W570*D530*H810</title><Manufacturer type="system" typeOfParameter="Text">Livart</Manufacturer><Model type="system" typeOfParameter="Text">OH 3010</Model><leg_support_material displayName="leg support material" type="custom" typeOfParameter="Material">gray plastic</leg_support_material><leg_material displayName="leg material" type="custom" typeOfParameter="Material">gray plastic</leg_material><knob_material displayName="knob material" type="custom" typeOfParameter="Material">gray plastic</knob_material><cushion_material displayName="cushion material" type="custom" typeOfParameter="Material">blue fabric-1</cushion_material></A:part></A:family></entry>
