<?xml version="1.0" encoding="UTF-8"?>
<entry xmlns="http://www.w3.org/2005/Atom" xmlns:A="urn:schemas-autodesk-com:partatom"><title>0547_M_FU_S_장식장2</title><id></id><updated>2010-07-24T02:56:27Z</updated><A:taxonomy><term>adsk:revit</term><label>Autodesk Revit</label></A:taxonomy><A:taxonomy><term>adsk:revit:grouping</term><label>Autodesk Revit Grouping</label></A:taxonomy><category><term>Furniture</term><scheme>adsk:revit:grouping</scheme></category><link rel="design-2d" type="application/rfa" href="."><A:design-file><A:title>0547_M_FU_S_장식장2.rfa</A:title><A:product>Revit</A:product><A:product-version>2009</A:product-version><A:updated>2010-07-24T02:56:27Z</A:updated></A:design-file></link><A:family type="user"><A:variationCount>2</A:variationCount><A:part type="user"><title>72" x 72" x 24"</title><Material type="custom" typeOfParameter="Material">&lt;By Category&gt;</Material><Assembly_Code displayName="Assembly Code" type="system" typeOfParameter="Text">E2020200</Assembly_Code><Center_Width displayName="Center Width" type="custom" typeOfParameter="Length" units="mm">813</Center_Width><Depth type="custom" typeOfParameter="Length" units="mm">610</Depth><Height type="custom" typeOfParameter="Length" units="mm">1829</Height><Width type="custom" typeOfParameter="Length" units="mm">1829</Width></A:part><A:part type="user"><title>96" x 84" x 30"</title><Material type="custom" typeOfParameter="Material">Laminate - Ivory, Matte</Material><Assembly_Code displayName="Assembly Code" type="system" typeOfParameter="Text">E2020200</Assembly_Code><Center_Width displayName="Center Width" type="custom" typeOfParameter="Length" units="mm">800</Center_Width><Depth type="custom" typeOfParameter="Length" units="mm">300</Depth><Height type="custom" typeOfParameter="Length" units="mm">2200</Height><Width type="custom" typeOfParameter="Length" units="mm">2500</Width></A:part></A:family></entry>
