<?xml version="1.0" encoding="UTF-8"?>
<entry xmlns="http://www.w3.org/2005/Atom" xmlns:A="urn:schemas-autodesk-com:partatom"><title>0083_M_DR_W_triple-glass 2</title><id></id><updated>2010-07-24T01:28:24Z</updated><A:taxonomy><term>adsk:revit</term><label>Autodesk Revit</label></A:taxonomy><A:taxonomy><term>adsk:revit:grouping</term><label>Autodesk Revit Grouping</label></A:taxonomy><category><term>Doors</term><scheme>adsk:revit:grouping</scheme></category><link rel="design-2d" type="application/rfa" href="."><A:design-file><A:title>0083_M_DR_W_triple-glass 2.rfa</A:title><A:product>Revit</A:product><A:product-version>8.0</A:product-version><A:updated>2010-07-24T01:28:24Z</A:updated></A:design-file></link><A:family type="user"><Host>Wall</Host><A:variationCount>5</A:variationCount><A:part type="user"><title>108" x 84"</title><Thickness type="system" typeOfParameter="Length">0' - 2"</Thickness><Muntin type="custom" typeOfParameter="Length">0' - 1"</Muntin><Function type="system">Interior</Function><Assembly_Code displayName="Assembly Code" type="system" typeOfParameter="Text">C1020</Assembly_Code><Door_Material displayName="Door Material" type="custom" typeOfParameter="Material">Door - Panel</Door_Material><Frame_Material displayName="Frame Material" type="custom" typeOfParameter="Material">Door - Frame</Frame_Material><Height type="system" typeOfParameter="Length">7' - 0"</Height><Rail_Width___Base displayName="Rail Width - Base" type="custom" typeOfParameter="Length">0' - 9 1/2"</Rail_Width___Base><Rail_Width___Top displayName="Rail Width - Top" type="custom" typeOfParameter="Length">0' - 5"</Rail_Width___Top><Stile_Width displayName="Stile Width" type="custom" typeOfParameter="Length">0' - 5"</Stile_Width><Trim_Projection displayName="Trim Projection" type="custom" typeOfParameter="Length">0' - 1"</Trim_Projection><Trim_Width displayName="Trim Width" type="custom" typeOfParameter="Length">0' - 3"</Trim_Width><Wall_Closure displayName="Wall Closure" type="system">By host</Wall_Closure><Width type="system" typeOfParameter="Length">9' - 0"</Width><Panel_Width displayName="Panel Width" type="custom" typeOfParameter="Length">3' - 0"</Panel_Width></A:part><A:part type="user"><title>96" x 80"</title><Thickness type="system" typeOfParameter="Length">0' - 2"</Thickness><Muntin type="custom" typeOfParameter="Length">0' - 1"</Muntin><Function type="system">Interior</Function><Assembly_Code displayName="Assembly Code" type="system" typeOfParameter="Text">C1020</Assembly_Code><Door_Material displayName="Door Material" type="custom" typeOfParameter="Material">Door - Panel</Door_Material><Frame_Material displayName="Frame Material" type="custom" typeOfParameter="Material">Door - Frame</Frame_Material><Height type="system" typeOfParameter="Length">6' - 8"</Height><Rail_Width___Base displayName="Rail Width - Base" type="custom" typeOfParameter="Length">0' - 9 1/2"</Rail_Width___Base><Rail_Width___Top displayName="Rail Width - Top" type="custom" typeOfParameter="Length">0' - 5"</Rail_Width___Top><Stile_Width displayName="Stile Width" type="custom" typeOfParameter="Length">0' - 5"</Stile_Width><Trim_Projection displayName="Trim Projection" type="custom" typeOfParameter="Length">0' - 1"</Trim_Projection><Trim_Width displayName="Trim Width" type="custom" typeOfParameter="Length">0' - 3"</Trim_Width><Wall_Closure displayName="Wall Closure" type="system">By host</Wall_Closure><Width type="system" typeOfParameter="Length">8' - 0"</Width><Panel_Width displayName="Panel Width" type="custom" typeOfParameter="Length">2' - 8"</Panel_Width></A:part><A:part type="user"><title>96" x 84"</title><Thickness type="system" typeOfParameter="Length">0' - 2"</Thickness><Muntin type="custom" typeOfParameter="Length">0' - 1"</Muntin><Function type="system">Interior</Function><Assembly_Code displayName="Assembly Code" type="system" typeOfParameter="Text">C1020</Assembly_Code><Door_Material displayName="Door Material" type="custom" typeOfParameter="Material">Door - Panel</Door_Material><Frame_Material displayName="Frame Material" type="custom" typeOfParameter="Material">Door - Frame</Frame_Material><Height type="system" typeOfParameter="Length">7' - 0"</Height><Rail_Width___Base displayName="Rail Width - Base" type="custom" typeOfParameter="Length">0' - 9 1/2"</Rail_Width___Base><Rail_Width___Top displayName="Rail Width - Top" type="custom" typeOfParameter="Length">0' - 5"</Rail_Width___Top><Stile_Width displayName="Stile Width" type="custom" typeOfParameter="Length">0' - 5"</Stile_Width><Trim_Projection displayName="Trim Projection" type="custom" typeOfParameter="Length">0' - 1"</Trim_Projection><Trim_Width displayName="Trim Width" type="custom" typeOfParameter="Length">0' - 3"</Trim_Width><Wall_Closure displayName="Wall Closure" type="system">By host</Wall_Closure><Width type="system" typeOfParameter="Length">8' - 0"</Width><Panel_Width displayName="Panel Width" type="custom" typeOfParameter="Length">2' - 8"</Panel_Width></A:part><A:part type="user"><title>108" x 82"</title><Thickness type="system" typeOfParameter="Length">0' - 2"</Thickness><Muntin type="custom" typeOfParameter="Length">0' - 1"</Muntin><Function type="system">Interior</Function><Assembly_Code displayName="Assembly Code" type="system" typeOfParameter="Text">C1020</Assembly_Code><Door_Material displayName="Door Material" type="custom" typeOfParameter="Material">Door - Panel</Door_Material><Frame_Material displayName="Frame Material" type="custom" typeOfParameter="Material">Door - Frame</Frame_Material><Height type="system" typeOfParameter="Length">6' - 10"</Height><Rail_Width___Base displayName="Rail Width - Base" type="custom" typeOfParameter="Length">0' - 9 1/2"</Rail_Width___Base><Rail_Width___Top displayName="Rail Width - Top" type="custom" typeOfParameter="Length">0' - 5"</Rail_Width___Top><Stile_Width displayName="Stile Width" type="custom" typeOfParameter="Length">0' - 5"</Stile_Width><Trim_Projection displayName="Trim Projection" type="custom" typeOfParameter="Length">0' - 1"</Trim_Projection><Trim_Width displayName="Trim Width" type="custom" typeOfParameter="Length">0' - 3"</Trim_Width><Wall_Closure displayName="Wall Closure" type="system">By host</Wall_Closure><Width type="system" typeOfParameter="Length">9' - 0"</Width><Panel_Width displayName="Panel Width" type="custom" typeOfParameter="Length">3' - 0"</Panel_Width></A:part><A:part type="user"><title>2438 x 2134mm</title><Thickness type="system" typeOfParameter="Length">0' - 2"</Thickness><Muntin type="custom" typeOfParameter="Length">0' - 1"</Muntin><Function type="system">Interior</Function><Door_Material displayName="Door Material" type="custom" typeOfParameter="Material">Door - Panel</Door_Material><Frame_Material displayName="Frame Material" type="custom" typeOfParameter="Material">Door - Frame</Frame_Material><Height type="system" typeOfParameter="Length">7' - 0"</Height><Rail_Width___Base displayName="Rail Width - Base" type="custom" typeOfParameter="Length">0' - 9 1/2"</Rail_Width___Base><Rail_Width___Top displayName="Rail Width - Top" type="custom" typeOfParameter="Length">0' - 5"</Rail_Width___Top><Stile_Width displayName="Stile Width" type="custom" typeOfParameter="Length">0' - 5"</Stile_Width><Trim_Projection displayName="Trim Projection" type="custom" typeOfParameter="Length">0' - 1"</Trim_Projection><Trim_Width displayName="Trim Width" type="custom" typeOfParameter="Length">0' - 3"</Trim_Width><Wall_Closure displayName="Wall Closure" type="system">By host</Wall_Closure><Width type="system" typeOfParameter="Length">8' - 0"</Width><Panel_Width displayName="Panel Width" type="custom" typeOfParameter="Length">2' - 8"</Panel_Width></A:part></A:family></entry>
