<?xml version="1.0" encoding="UTF-8"?>
<entry xmlns="http://www.w3.org/2005/Atom" xmlns:A="urn:schemas-autodesk-com:partatom"><title>싱크대 화장대-정사각형</title><id></id><updated>2010-07-24T04:38:48Z</updated><A:taxonomy><term>adsk:revit</term><label>Autodesk Revit</label></A:taxonomy><A:taxonomy><term>adsk:revit:grouping</term><label>Autodesk Revit Grouping</label></A:taxonomy><category><term>Plumbing Fixtures</term><scheme>adsk:revit:grouping</scheme></category><link rel="design-2d" type="application/rfa" href="."><A:design-file><A:title>싱크대 화장대-정사각형.rfa</A:title><A:product>Revit</A:product><A:product-version>2009</A:product-version><A:updated>2010-07-24T04:38:48Z</A:updated></A:design-file></link><A:family type="user"><A:variationCount>1</A:variationCount><A:part type="user"><title>500 x 440mm</title><______ displayName="세면기 재료" type="custom" typeOfParameter="Material">자기 - 리넨</______><깊_ displayName="깊이" type="custom" typeOfParameter="Length" units="mm">440.00</깊_><_____ displayName="설비 재료" type="custom" typeOfParameter="Material">금속 - 스틸, 광택</_____><폭 type="custom" typeOfParameter="Length" units="mm">500.00</폭></A:part></A:family></entry>
