<?xml version="1.0" encoding="UTF-8"?>
<entry xmlns="http://www.w3.org/2005/Atom" xmlns:A="urn:schemas-autodesk-com:partatom"><title>0065_M_FU_S_Bed with Padded Back</title><id></id><updated>2010-07-24T02:20:11Z</updated><A:taxonomy><term>adsk:revit</term><label>Autodesk Revit</label></A:taxonomy><A:taxonomy><term>adsk:revit:grouping</term><label>Autodesk Revit Grouping</label></A:taxonomy><category><term>Furniture</term><scheme>adsk:revit:grouping</scheme></category><link rel="design-2d" type="application/rfa" href="."><A:design-file><A:title>0065_M_FU_S_Bed with Padded Back.rfa</A:title><A:product>Revit</A:product><A:product-version>2009</A:product-version><A:updated>2010-07-24T02:20:11Z</A:updated></A:design-file></link><A:family type="user"><A:variationCount>4</A:variationCount><A:part type="user"><title>180 x 200 cm</title><Manufacturer type="system" typeOfParameter="Text">Revit</Manufacturer><Materiale_Letto displayName="Materiale Letto" type="custom" typeOfParameter="Material">&lt;By Category&gt;</Materiale_Letto><Materiale_Gambe displayName="Materiale Gambe" type="custom" typeOfParameter="Material">&lt;By Category&gt;</Materiale_Gambe><Larghezza type="custom" typeOfParameter="Length" units="mm">1800</Larghezza></A:part><A:part type="user"><title>160 x 200 cm</title><Manufacturer type="system" typeOfParameter="Text">Revit</Manufacturer><Materiale_Letto displayName="Materiale Letto" type="custom" typeOfParameter="Material">&lt;By Category&gt;</Materiale_Letto><Materiale_Gambe displayName="Materiale Gambe" type="custom" typeOfParameter="Material">&lt;By Category&gt;</Materiale_Gambe><Larghezza type="custom" typeOfParameter="Length" units="mm">1600</Larghezza></A:part><A:part type="user"><title>140 x 200 cm</title><Manufacturer type="system" typeOfParameter="Text">Revit</Manufacturer><Materiale_Letto displayName="Materiale Letto" type="custom" typeOfParameter="Material">&lt;By Category&gt;</Materiale_Letto><Materiale_Gambe displayName="Materiale Gambe" type="custom" typeOfParameter="Material">&lt;By Category&gt;</Materiale_Gambe><Larghezza type="custom" typeOfParameter="Length" units="mm">1400</Larghezza></A:part><A:part type="user"><title>120 x 200 cm</title><Manufacturer type="system" typeOfParameter="Text">Revit</Manufacturer><Materiale_Letto displayName="Materiale Letto" type="custom" typeOfParameter="Material">&lt;By Category&gt;</Materiale_Letto><Materiale_Gambe displayName="Materiale Gambe" type="custom" typeOfParameter="Material">&lt;By Category&gt;</Materiale_Gambe><Larghezza type="custom" typeOfParameter="Length" units="mm">1200</Larghezza></A:part></A:family></entry>
