<?xml version="1.0" encoding="UTF-8"?>
<entry xmlns="http://www.w3.org/2005/Atom" xmlns:A="urn:schemas-autodesk-com:partatom"><title>0962_M_FU_S_침대-침낭</title><id></id><updated>2010-07-24T03:46:31Z</updated><A:taxonomy><term>adsk:revit</term><label>Autodesk Revit</label></A:taxonomy><A:taxonomy><term>adsk:revit:grouping</term><label>Autodesk Revit Grouping</label></A:taxonomy><category><term>Furniture</term><scheme>adsk:revit:grouping</scheme></category><link rel="design-2d" type="application/rfa" href="."><A:design-file><A:title>0962_M_FU_S_침대-침낭.rfa</A:title><A:product>Revit</A:product><A:product-version>8.0</A:product-version><A:updated>2010-07-24T03:46:31Z</A:updated></A:design-file></link><A:family type="user"><A:variationCount>1</A:variationCount><A:part type="user"><title>2083 x 0915 x 1500mm</title><_레____ displayName="프레임 재료" type="custom" typeOfParameter="Material">목재 - 자작나무</_레____><_높_ displayName="높이" type="custom" typeOfParameter="Length" units="mm">1500.00</_높_><_길_ displayName="길이" type="custom" typeOfParameter="Length" units="mm">2083.00</_길_><_______ displayName="매트리스 재료" type="custom" typeOfParameter="Material">직물 - 흰색</_______><폭 type="custom" typeOfParameter="Length" units="mm">915.00</폭></A:part></A:family></entry>
