<?xml version="1.0" encoding="UTF-8"?>
<entry xmlns="http://www.w3.org/2005/Atom" xmlns:A="urn:schemas-autodesk-com:partatom"><title>파일-HP 파일</title><id></id><updated>2010-07-24T05:09:54Z</updated><A:taxonomy><term>adsk:revit</term><label>Autodesk Revit</label></A:taxonomy><A:taxonomy><term>adsk:revit:grouping</term><label>Autodesk Revit Grouping</label></A:taxonomy><category><term>Structural Foundations</term><scheme>adsk:revit:grouping</scheme></category><link rel="design-2d" type="application/rfa" href="."><A:design-file><A:title>파일-HP 파일.rfa</A:title><A:product>Revit</A:product><A:product-version>2009</A:product-version><A:updated>2010-07-24T05:09:54Z</A:updated></A:design-file></link><A:family type="user"><A:variationCount>11</A:variationCount><A:part type="user"><title>HP200X53</title><tw type="custom" typeOfParameter="Length" units="mm">11</tw><tf type="custom" typeOfParameter="Length" units="mm">11</tf><k type="custom" typeOfParameter="Length" units="mm">29</k><d type="custom" typeOfParameter="Length" units="mm">204</d><bf type="custom" typeOfParameter="Length" units="mm">207</bf><W type="custom" typeOfParameter="Number">0.525</W><최___포 displayName="최소 내포" type="custom" typeOfParameter="Length" units="mm">150</최___포><Depth type="shared" id="be628205-479e-4a9b-895c-fcb505ec2847" typeOfParameter="Length" units="mm">6000</Depth><Assembly_Code displayName="Assembly Code" type="system" typeOfParameter="Text">A1020140</Assembly_Code><A type="custom" typeOfParameter="Area" units="m²">0.01</A></A:part><A:part type="user"><title>HP250X62</title><tw type="custom" typeOfParameter="Length" units="mm">11</tw><tf type="custom" typeOfParameter="Length" units="mm">11</tf><k type="custom" typeOfParameter="Length" units="mm">28</k><d type="custom" typeOfParameter="Length" units="mm">246</d><bf type="custom" typeOfParameter="Length" units="mm">256</bf><W type="custom" typeOfParameter="Number">0.613</W><최___포 displayName="최소 내포" type="custom" typeOfParameter="Length" units="mm">150</최___포><Depth type="shared" id="be628205-479e-4a9b-895c-fcb505ec2847" typeOfParameter="Length" units="mm">6000</Depth><Assembly_Code displayName="Assembly Code" type="system" typeOfParameter="Text">A1020140</Assembly_Code><A type="custom" typeOfParameter="Area" units="m²">0.01</A></A:part><A:part type="user"><title>HP250X85</title><tw type="custom" typeOfParameter="Length" units="mm">14</tw><tf type="custom" typeOfParameter="Length" units="mm">14</tf><k type="custom" typeOfParameter="Length" units="mm">32</k><d type="custom" typeOfParameter="Length" units="mm">254</d><bf type="custom" typeOfParameter="Length" units="mm">260</bf><W type="custom" typeOfParameter="Number">0.832</W><최___포 displayName="최소 내포" type="custom" typeOfParameter="Length" units="mm">150</최___포><Depth type="shared" id="be628205-479e-4a9b-895c-fcb505ec2847" typeOfParameter="Length" units="mm">6000</Depth><Assembly_Code displayName="Assembly Code" type="system" typeOfParameter="Text">A1020140</Assembly_Code><A type="custom" typeOfParameter="Area" units="m²">0.01</A></A:part><A:part type="user"><title>HP310X79</title><tw type="custom" typeOfParameter="Length" units="mm">11</tw><tf type="custom" typeOfParameter="Length" units="mm">11</tf><k type="custom" typeOfParameter="Length" units="mm">28</k><d type="custom" typeOfParameter="Length" units="mm">299</d><bf type="custom" typeOfParameter="Length" units="mm">306</bf><W type="custom" typeOfParameter="Number">0.773</W><최___포 displayName="최소 내포" type="custom" typeOfParameter="Length" units="mm">150</최___포><Depth type="shared" id="be628205-479e-4a9b-895c-fcb505ec2847" typeOfParameter="Length" units="mm">6000</Depth><Assembly_Code displayName="Assembly Code" type="system" typeOfParameter="Text">A1020140</Assembly_Code><A type="custom" typeOfParameter="Area" units="m²">0.01</A></A:part><A:part type="user"><title>HP310X93</title><tw type="custom" typeOfParameter="Length" units="mm">13</tw><tf type="custom" typeOfParameter="Length" units="mm">13</tf><k type="custom" typeOfParameter="Length" units="mm">30</k><d type="custom" typeOfParameter="Length" units="mm">303</d><bf type="custom" typeOfParameter="Length" units="mm">308</bf><W type="custom" typeOfParameter="Number">0.919</W><최___포 displayName="최소 내포" type="custom" typeOfParameter="Length" units="mm">150</최___포><Depth type="shared" id="be628205-479e-4a9b-895c-fcb505ec2847" typeOfParameter="Length" units="mm">6000</Depth><Assembly_Code displayName="Assembly Code" type="system" typeOfParameter="Text">A1020140</Assembly_Code><A type="custom" typeOfParameter="Area" units="m²">0.01</A></A:part><A:part type="user"><title>HP310X110</title><tw type="custom" typeOfParameter="Length" units="mm">15</tw><tf type="custom" typeOfParameter="Length" units="mm">15</tf><k type="custom" typeOfParameter="Length" units="mm">33</k><d type="custom" typeOfParameter="Length" units="mm">308</d><bf type="custom" typeOfParameter="Length" units="mm">310</bf><W type="custom" typeOfParameter="Number">1.08</W><최___포 displayName="최소 내포" type="custom" typeOfParameter="Length" units="mm">150</최___포><Depth type="shared" id="be628205-479e-4a9b-895c-fcb505ec2847" typeOfParameter="Length" units="mm">6000</Depth><Assembly_Code displayName="Assembly Code" type="system" typeOfParameter="Text">A1020140</Assembly_Code><A type="custom" typeOfParameter="Area" units="m²">0.01</A></A:part><A:part type="user"><title>HP310X125</title><tw type="custom" typeOfParameter="Length" units="mm">17</tw><tf type="custom" typeOfParameter="Length" units="mm">17</tf><k type="custom" typeOfParameter="Length" units="mm">35</k><d type="custom" typeOfParameter="Length" units="mm">312</d><bf type="custom" typeOfParameter="Length" units="mm">312</bf><W type="custom" typeOfParameter="Number">1.23</W><최___포 displayName="최소 내포" type="custom" typeOfParameter="Length" units="mm">150</최___포><Depth type="shared" id="be628205-479e-4a9b-895c-fcb505ec2847" typeOfParameter="Length" units="mm">6000</Depth><Assembly_Code displayName="Assembly Code" type="system" typeOfParameter="Text">A1020140</Assembly_Code><A type="custom" typeOfParameter="Area" units="m²">0.02</A></A:part><A:part type="user"><title>HP360X108</title><tw type="custom" typeOfParameter="Length" units="mm">13</tw><tf type="custom" typeOfParameter="Length" units="mm">13</tf><k type="custom" typeOfParameter="Length" units="mm">30</k><d type="custom" typeOfParameter="Length" units="mm">346</d><bf type="custom" typeOfParameter="Length" units="mm">370</bf><W type="custom" typeOfParameter="Number">1.07</W><최___포 displayName="최소 내포" type="custom" typeOfParameter="Length" units="mm">150</최___포><Depth type="shared" id="be628205-479e-4a9b-895c-fcb505ec2847" typeOfParameter="Length" units="mm">6000</Depth><Assembly_Code displayName="Assembly Code" type="system" typeOfParameter="Text">A1020140</Assembly_Code><A type="custom" typeOfParameter="Area" units="m²">0.01</A></A:part><A:part type="user"><title>HP360X132</title><tw type="custom" typeOfParameter="Length" units="mm">16</tw><tf type="custom" typeOfParameter="Length" units="mm">16</tf><k type="custom" typeOfParameter="Length" units="mm">33</k><d type="custom" typeOfParameter="Length" units="mm">351</d><bf type="custom" typeOfParameter="Length" units="mm">373</bf><W type="custom" typeOfParameter="Number">1.3</W><최___포 displayName="최소 내포" type="custom" typeOfParameter="Length" units="mm">150</최___포><Depth type="shared" id="be628205-479e-4a9b-895c-fcb505ec2847" typeOfParameter="Length" units="mm">6000</Depth><Assembly_Code displayName="Assembly Code" type="system" typeOfParameter="Text">A1020140</Assembly_Code><A type="custom" typeOfParameter="Area" units="m²">0.02</A></A:part><A:part type="user"><title>HP360X152</title><tw type="custom" typeOfParameter="Length" units="mm">18</tw><tf type="custom" typeOfParameter="Length" units="mm">18</tf><k type="custom" typeOfParameter="Length" units="mm">35</k><d type="custom" typeOfParameter="Length" units="mm">356</d><bf type="custom" typeOfParameter="Length" units="mm">376</bf><W type="custom" typeOfParameter="Number">1.49</W><최___포 displayName="최소 내포" type="custom" typeOfParameter="Length" units="mm">150</최___포><Depth type="shared" id="be628205-479e-4a9b-895c-fcb505ec2847" typeOfParameter="Length" units="mm">6000</Depth><Assembly_Code displayName="Assembly Code" type="system" typeOfParameter="Text">A1020140</Assembly_Code><A type="custom" typeOfParameter="Area" units="m²">0.02</A></A:part><A:part type="user"><title>HP360X174</title><tw type="custom" typeOfParameter="Length" units="mm">20</tw><tf type="custom" typeOfParameter="Length" units="mm">20</tf><k type="custom" typeOfParameter="Length" units="mm">38</k><d type="custom" typeOfParameter="Length" units="mm">361</d><bf type="custom" typeOfParameter="Length" units="mm">378</bf><W type="custom" typeOfParameter="Number">1.71</W><최___포 displayName="최소 내포" type="custom" typeOfParameter="Length" units="mm">150</최___포><Depth type="shared" id="be628205-479e-4a9b-895c-fcb505ec2847" typeOfParameter="Length" units="mm">6000</Depth><Assembly_Code displayName="Assembly Code" type="system" typeOfParameter="Text">A1020140</Assembly_Code><A type="custom" typeOfParameter="Area" units="m²">0.02</A></A:part></A:family></entry>
